mylove/__init__.py
mylove-1.1.0.dist-info/LICENCE.txt
mylove-1.1.0.dist-info/METADATA
mylove-1.1.0.dist-info/WHEEL
mylove-1.1.0.dist-info/top_level.txt
mylove-1.1.0.dist-info/RECORD
