Metadata-Version: 2.1
Name: mylove
Version: 1.1.0
Summary: Drawing picture for loves
Home-page: 
Author: Umidyor
Author-email: umidyor007@gmail.com
License: MIT
Keywords: drawing love,love picture
Classifier: Development Status :: 5 - Production/Stable
Classifier: Intended Audience :: Education
Classifier: Operating System :: Microsoft :: Windows :: Windows 10
Classifier: License :: OSI Approved :: MIT License
Classifier: Programming Language :: Python :: 3
License-File: LICENCE.txt
Requires-Dist: pillow
Requires-Dist: requests
